{
    "Arlan": "아를란",
    "Asta": "아스타",
    "Bailu": "백로",
    "Bronya": "브로냐",
    "Boothill": "부트힐",
    "DanHeng": "단항",
    "DanHengImbibitorLunae": "단항·음월",
    "DanHengPermansorTerrae": "단항·등황",
    "Jade": "제이드",
    "Feixiao": "비소",
    "FuXuan": "부현",
    "Guinaifen": "계네빈",
    "Huohuo": "곽향",
    "Sparkle": "스파클",
    "Hook": "후크",
    "Acheron": "아케론",
    "Herta": "헤르타",
    "BlackSwan": "블랙 스완",
    "Hanya": "한아",
    "Jingliu": "경류",
    "Gallagher": "갤러거",
    "Gepard": "게파드",
    "Jiaoqiu": "초구",
    "JingYuan": "경원",
    "Himeko": "히메코",
    "Kafka": "카프카",
    "Clara": "클라라",
    "Luocha": "나찰",
    "Luka": "루카",
    "Lynx": "링스",
    "Rappa": "라파",
    "Lingsha": "영사",
    "Firefly": "반디",
    "FireflySpringMissive": "반디·봄날의 선물",
    "Misha": "미샤",
    "Moze": "맥택",
    "Natasha": "나타샤",
    "Pela": "페라",
    "Qingque": "청작",
    "CaelumPreservation": "개척자(남)·보존",
    "CaelumDestruction": "개척자(남)·파멸",
    "CaelumImaginary": "개척자(남)·화합",
    "CaelumRemembrance": "개척자(남)·기억",
    "Blade": "블레이드",
    "RuanMei": "완·매",
    "Sampo": "삼포",
    "Aventurine": "어벤츄린",
    "Sushang": "소상",
    "March7th": "Mar. 7th (얼음)",
    "March7thImaginary": "Mar. 7th (허수)",
    "March7thNascentSpring": "Mar. 7th·겨울이 가고 찾아온 봄",
    "TopazandNumby": "토파즈&복순이",
    "Tingyun": "정운",
    "Welt": "웰트",
    "Seele": "제레",
    "Serval": "서벌",
    "Sunday": "선데이",
    "Xueyi": "설의",
    "StellePreservation": "개척자(여)·보존",
    "StelleDestruction": "개척자(여)·파멸",
    "StelleImaginary": "개척자(여)·화합",
    "StelleRemembrance": "개척자(여)·기억",
    "Yukong": "어공",
    "SilverWolf": "은랑",
    "Yunli": "운리",
    "Yanqing": "연경",
    "Argenti": "아젠티",
    "Robin": "로빈",
    "DrRatio": "Dr. 레이시오",
    "Fugue": "망귀인",
    "TheHerta": "더헤르타",
    "Aglaea": "아글라이아",
    "Tribbie": "트리비",
    "Mydei": "마이데이",
    "Castorice": "카스토리스",
    "Anaxa": "아낙사",
    "Hyacine": "히아킨",
    "Cipher": "사이퍼",
    "Phainon": "파이논",
    "Archer": "아처",
    "Saber": "세이버",
    "Hysilens": "히실렌스",
    "Cerydra": "케리드라",
    "Evernight": "에버나이트",
    "Cyrene": "키레네",
    "TheDahlia": "다알리아"
}